vpp_config.py
vpp_config-20.5.1.data/data/vpp/vpp-config/configs/auto-config.yaml
vpp_config-20.5.1.data/data/vpp/vpp-config/configs/cloud-config.iso
vpp_config-20.5.1.data/data/vpp/vpp-config/configs/iperf-centos.xml.template
vpp_config-20.5.1.data/data/vpp/vpp-config/configs/iperf-ubuntu.xml.template
vpp_config-20.5.1.data/data/vpp/vpp-config/dryrun/default/grub.template
vpp_config-20.5.1.data/data/vpp/vpp-config/dryrun/sysctl.d/80-vpp.conf.template
vpp_config-20.5.1.data/data/vpp/vpp-config/dryrun/vpp/startup.conf.template
vpp_config-20.5.1.data/data/vpp/vpp-config/scripts/dpdk-devbind.py
vpp_config-20.5.1.dist-info/DESCRIPTION.rst
vpp_config-20.5.1.dist-info/METADATA
vpp_config-20.5.1.dist-info/RECORD
vpp_config-20.5.1.dist-info/WHEEL
vpp_config-20.5.1.dist-info/entry_points.txt
vpp_config-20.5.1.dist-info/metadata.json
vpp_config-20.5.1.dist-info/top_level.txt
vpplib/AutoConfig.py
vpplib/CpuUtils.py
vpplib/QemuUtils.py
vpplib/VPPUtil.py
vpplib/VppGrubUtil.py
vpplib/VppHugePageUtil.py
vpplib/VppPCIUtil.py
vpplib/__init__.py
vpplib/constants.py
