Metadata-Version: 2.0
Name: vpp-config
Version: 20.5.1
Summary: VPP Configuration Utility
Home-page: https://wiki.fd.io/view/VPP
Author: John DeNisco
Author-email: jdenisco@cisco.com
License: Apache-2.0
Keywords: vppconfig
Platform: UNKNOWN
Requires-Dist: distro
Requires-Dist: pyyaml
Requires-Dist: requests
